simple_plugin.py
simple_plugin2-1.0.dist-info/LICENSE
simple_plugin2-1.0.dist-info/METADATA
simple_plugin2-1.0.dist-info/WHEEL
simple_plugin2-1.0.dist-info/entry_points.txt
simple_plugin2-1.0.dist-info/top_level.txt
simple_plugin2-1.0.dist-info/RECORD
